agent_society_mcp_client_wrapper-0.0.3.dist-info/licenses/LICENSE
mcpwrap/__init__.py
mcpwrap/client.py
mcpwrap/llm_integration.py
mcpwrap/multi_mcp_model.py
mcpwrap/server_stub.py
agent_society_mcp_client_wrapper-0.0.3.dist-info/METADATA
agent_society_mcp_client_wrapper-0.0.3.dist-info/WHEEL
agent_society_mcp_client_wrapper-0.0.3.dist-info/top_level.txt
agent_society_mcp_client_wrapper-0.0.3.dist-info/RECORD
