Metadata-Version: 2.4
Name: agent-society-mcp-client-wrapper
Version: 0.0.3
Summary: A Python library which wraps around Anthropic's low-level MCP client
Author: Agent Society
Classifier: Programming Language :: Python :: 3
Classifier: Operating System :: OS Independent
Requires-Python: >=3.12.8
License-File: LICENSE
Requires-Dist: mcp==1.9.4
Requires-Dist: langchain==0.3.26
Requires-Dist: jsonref==1.1.0
Requires-Dist: pydantic==2.11.7
Dynamic: license-file
